logiclayer_complexity/__init__.py
logiclayer_complexity/common.py
logiclayer_complexity/complexity/__init__.py
logiclayer_complexity/complexity/dependencies.py
logiclayer_complexity/complexity/structs.py
logiclayer_complexity/dependencies.py
logiclayer_complexity/exceptions.py
logiclayer_complexity/module.py
logiclayer_complexity/opportunity_gain.py
logiclayer_complexity/pmi/__init__.py
logiclayer_complexity/pmi/peii.py
logiclayer_complexity/pmi/pgi.py
logiclayer_complexity/rca/__init__.py
logiclayer_complexity/rca/dependencies.py
logiclayer_complexity/rca/structs.py
logiclayer_complexity/relatedness/__init__.py
logiclayer_complexity/relatedness/dependencies.py
logiclayer_complexity/relatedness/structs.py
logiclayer_complexity/response.py
logiclayer_complexity/structs.py
logiclayer_complexity/wdi.py
logiclayer_complexity-0.7.2.dist-info/METADATA
logiclayer_complexity-0.7.2.dist-info/WHEEL
logiclayer_complexity-0.7.2.dist-info/licenses/LICENSE
logiclayer_complexity-0.7.2.dist-info/RECORD
