Metadata-Version: 2.4
Name: logiclayer-complexity
Version: 0.7.2
Summary: LogicLayer module to enable Economic Complexity calculations, using data from a tesseract-olap server.
License: Proprietary
License-File: LICENSE
Author: Francisco Abarzua
Author-email: francisco@datawheel.us
Maintainer: Francisco Abarzua
Maintainer-email: francisco@datawheel.us
Requires-Python: ~=3.9
Classifier: License :: Other/Proprietary License
Classifier: Programming Language :: Python :: 3
Classifier: Programming Language :: Python :: 3.9
Classifier: Programming Language :: Python :: 3.10
Classifier: Programming Language :: Python :: 3.11
Classifier: Programming Language :: Python :: 3.12
Classifier: Programming Language :: Python :: 3.13
Classifier: Programming Language :: Python :: 3.14
Classifier: Topic :: Software Development :: Libraries :: Python Modules
Requires-Dist: economic-complexity (>=0.2.4)
Requires-Dist: logiclayer (>=0.4.1)
Requires-Dist: numpy (<2.0)
Requires-Dist: orjson (>=3.8)
Requires-Dist: pandas (>=1.5,<3.0)
Requires-Dist: polars (>=1.0,<2.0)
Requires-Dist: pyarrow (>=15.0)
Requires-Dist: tesseract-olap (>=0.18.8)
Project-URL: Repository, https://github.com/Datawheel/logiclayer-complexity
